gladiaio_sdk/__init__.py
gladiaio_sdk/client.py
gladiaio_sdk/client_options.py
gladiaio_sdk/py.typed
gladiaio_sdk/version.py
gladiaio_sdk/network/__init__.py
gladiaio_sdk/network/helper.py
gladiaio_sdk/network/http_client.py
gladiaio_sdk/network/websocket_client.py
gladiaio_sdk/v2/live/async_client.py
gladiaio_sdk/v2/live/async_session.py
gladiaio_sdk/v2/live/client.py
gladiaio_sdk/v2/live/generated_types.py
gladiaio_sdk/v2/live/session.py
gladiaio_sdk/v2/live/types.py
gladiaio_sdk-0.3.1.dist-info/METADATA
gladiaio_sdk-0.3.1.dist-info/WHEEL
gladiaio_sdk-0.3.1.dist-info/RECORD
