Metadata-Version: 2.4
Name: gladiaio-sdk
Version: 0.3.1
Summary: Gladia SDK for Python
Requires-Python: <4,>=3.10
Requires-Dist: anyio==4.11.0
Requires-Dist: certifi==2025.8.3
Requires-Dist: dataclasses-json==0.6.7
Requires-Dist: exceptiongroup==1.3.0; python_full_version < '3.11'
Requires-Dist: h11==0.16.0
Requires-Dist: httpcore==1.0.9
Requires-Dist: httpx==0.28.1
Requires-Dist: idna==3.10
Requires-Dist: marshmallow==3.26.1
Requires-Dist: mypy-extensions==1.1.0
Requires-Dist: packaging==25.0
Requires-Dist: pyee==13.0.0
Requires-Dist: sniffio==1.3.1
Requires-Dist: typing-extensions==4.15.0
Requires-Dist: typing-inspect==0.9.0
Requires-Dist: websockets==15.0.1
